{"_invocation_id": "7ef08c69-d82d-4dae-843a-f00614bf0810", "linked": {"0": {"name": "source.mini_project_dbt.raw_data.CUSTOMERS_TABLE", "type": "source", "succ": [5]}, "1": {"name": "source.mini_project_dbt.raw_data.PRODUCTS_TABLE", "type": "source", "succ": [6]}, "2": {"name": "source.mini_project_dbt.raw_data.TRANSACTIONS_TABLE", "type": "source", "succ": [7]}, "3": {"name": "source.mini_project_dbt.raw_data.COUNTRY_REGION_TABLE", "type": "source", "succ": [4]}, "4": {"name": "model.mini_project_dbt.staging_country_region_table", "type": "model"}, "5": {"name": "model.mini_project_dbt.staging_customers_table", "type": "model"}, "6": {"name": "model.mini_project_dbt.staging_products_table", "type": "model"}, "7": {"name": "model.mini_project_dbt.staging_transactions_table", "type": "model", "succ": [8, 9, 10, 11, 12, 13, 14]}, "8": {"name": "model.mini_project_dbt.new_logos_fiscal_year", "type": "model"}, "9": {"name": "model.mini_project_dbt.cross_sell_product_churn", "type": "model"}, "10": {"name": "model.mini_project_dbt.customer_revenue_ranking", "type": "model"}, "11": {"name": "model.mini_project_dbt.churn_new_customer", "type": "model"}, "12": {"name": "model.mini_project_dbt.product_revenue_ranking", "type": "model"}, "13": {"name": "model.mini_project_dbt.revenue_loss", "type": "model"}, "14": {"name": "model.mini_project_dbt.nrr_grr", "type": "model"}}}